{
  "$schema": "http://json-schema.org/draft-04/schema#",
  "id": "http://cpp.moj.gov.uk/prosecution/casefile/dlrm/json/schemas/pcf-definitions.json",
  "definitions": {
    "submissionStatus": {
      "type": "string",
      "enum": [
        "PENDING",
        "FAILED",
        "REJECTED",
        "SUCCESS",
        "SUCCESS_WITH_WARNINGS"
      ]
    },
    "channel": {
      "id": "http://cpp.moj.gov.uk/prosecution/casefile/dlrm/json/schemas/channel.json",
      "type": "string",
      "enum": [
        "SPI",
        "CPPI",
        "MCC",
        "CIVIL",
        "DLRM_MIGRATION"
      ]
    },
    "nationalInsuranceNumber": {
      "type": "string",
      "pattern": "^(?!BG)(?!GB)(?!NK)(?!KN)(?!TN)(?!NT)(?!ZZ)[A-CEGHJ-PR-TW-Z][A-CEGHJ-NPR-TW-Z][0-9][0-9][0-9][0-9][0-9][0-9][A-D]$"
    },

    "isoDate": {
      "type": "string",
      "pattern": "^\\d{4}-[01]\\d-[0-3]\\d$"
    },
    "jurisdiction": {
      "id": "http://cpp.moj.gov.uk/prosecution/casefile/dlrm/json/schemas/jurisdiction.json",
      "type": "string",
      "enum": ["CROWN", "MAGISTRATES", "EITHER"],
      "description": "Jurisdiction under which the verdict falls"
    }
  }
}